.gitignore
LICENSE
MANIFEST.in
setup.py
bflb_flash_command/BLFlashCommand.py
bflb_flash_command/__init__.py
bflb_flash_command/__main__.py
bflb_flash_command/config.py
bflb_flash_command.egg-info/PKG-INFO
bflb_flash_command.egg-info/SOURCES.txt
bflb_flash_command.egg-info/dependency_links.txt
bflb_flash_command.egg-info/entry_points.txt
bflb_flash_command.egg-info/not-zip-safe
bflb_flash_command.egg-info/requires.txt
bflb_flash_command.egg-info/top_level.txt
bflb_flash_command/chips/bl602/eflash_loader/eflash_loader.elf
bflb_flash_command/chips/bl602/eflash_loader/eflash_loader.map
bflb_flash_command/chips/bl602/eflash_loader/eflash_loader_24m.bin
bflb_flash_command/chips/bl602/eflash_loader/eflash_loader_26m.bin
bflb_flash_command/chips/bl602/eflash_loader/eflash_loader_32m.bin
bflb_flash_command/chips/bl602/eflash_loader/eflash_loader_38p4m.bin
bflb_flash_command/chips/bl602/eflash_loader/eflash_loader_40m.bin
bflb_flash_command/chips/bl602/eflash_loader/eflash_loader_40m_encrypt.bin
bflb_flash_command/chips/bl602/eflash_loader/eflash_loader_cfg.conf
bflb_flash_command/chips/bl602/eflash_loader/eflash_loader_none.bin
bflb_flash_command/chips/bl602/eflash_loader/eflash_loader_rc32m.bin
bflb_flash_command/chips/bl602/efuse_bootheader/efuse_bootheader_cfg.conf
bflb_flash_command/chips/bl602/efuse_bootheader/flash_para.bin
bflb_flash_command/chips/bl606p/eflash_loader/eflash_loader_cfg.conf
bflb_flash_command/chips/bl606p/efuse_bootheader/clock_para.bin
bflb_flash_command/chips/bl606p/efuse_bootheader/efuse_bootheader_cfg.conf
bflb_flash_command/chips/bl606p/efuse_bootheader/flash_para.bin
bflb_flash_command/chips/bl616/eflash_loader/eflash_loader_cfg.conf
bflb_flash_command/chips/bl616/efuse_bootheader/efuse_bootheader_cfg.conf
bflb_flash_command/chips/bl616/efuse_bootheader/flash_para.bin
bflb_flash_command/chips/bl616d/eflash_loader/eflash_loader_cfg.conf
bflb_flash_command/chips/bl616d/efuse_bootheader/efuse_bootheader_cfg.conf
bflb_flash_command/chips/bl616d/efuse_bootheader/flash_para.bin
bflb_flash_command/chips/bl616l/eflash_loader/eflash_loader_cfg.conf
bflb_flash_command/chips/bl616l/efuse_bootheader/efuse_bootheader_cfg.conf
bflb_flash_command/chips/bl616l/efuse_bootheader/flash_para.bin
